{"id":"dipplin","name":"Dipplin","number":1011,"type":["grass","dragon"],"size":"tiny","sr":7,"minLevel":5,"eggGroup":["grass","dragon"],"gender":"1:1","description":"The Candy Apple Pokémon. Dipplin is two creatures in one Pokémon. Its evolution was triggered by a special apple grown only in one place.","ac":17,"hitDice":"d10","speed":[{"type":"walking","value":15}],"attributes":{"str":15,"dex":10,"con":16,"int":6,"wis":14,"cha":12},"hp":50,"skills":["stealth","deception"],"savingThrows":["str","cha"],"senses":[{"type":"darkvision","value":30}],"abilities":[{"id":"supersweet-syrup","name":"Supersweet Syrup","description":"Attack rolls made against creatures within 30ft of this Pokémon gain 1d4 on the roll. Creatures with no sense of smell are not affected by this ability.","hidden":false},{"id":"gluttony","name":"Gluttony","description":"This Pokémon must eat its held berry when it falls below ½ of its maximum HP.","hidden":false},{"id":"sticky-hold","name":"Sticky Hold","description":"Held items cannot be stolen or knocked away from this Pokémon.","hidden":true}],"moves":{"start":["withdraw","sweet-scent","recycle","astonish","double-hit","growth","dragon-tail"],"level6":["dragon-breath","protect","bullet-seed"],"level10":["syrup-bomb","dragon-pulse"],"level14":["recover"],"level18":["substitute","energy-ball"],"tm":[11,15,17,22,33,42,44,53,68,74,82,86,88,90,101,102,133,136,141,145,166,169,179,184,196,197,203,205,212,223,253]},"media":{"main":"https://raw.githubusercontent.com/PokeAPI/sprites/master/sprites/pokemon/other/official-artwork/1011.png","mainShiny":"https://raw.githubusercontent.com/PokeAPI/sprites/master/sprites/pokemon/other/official-artwork/shiny/1011.png","sprite":"https://raw.githubusercontent.com/PokeAPI/sprites/master/sprites/pokemon/1011.png","spriteShiny":"https://raw.githubusercontent.com/PokeAPI/sprites/master/sprites/pokemon/shiny/1011.png"}}