{"id":"laser-focus","name":"Foco a Laser","type":"normal","power":"none","time":"1 ação","pp":15,"duration":"1 rodada, concentração","range":"self","description":["Ao ativar este movimento, você passa sua ação concentrando-se intensamente. Se mantiver sua concentração, seu primeiro ataque no próximo turno sempre será um acerto crítico."],"pokemon":[{"id":"mewtwo","name":"Mewtwo"},{"id":"lucario","name":"Lucario"},{"id":"kartana","name":"Kartana"},{"id":"marshadow","name":"Marshadow"},{"id":"arrokuda","name":"Arrokuda"},{"id":"barraskewda","name":"Barraskewda"},{"id":"duraludon","name":"Duraludon"},{"id":"zacian","name":"Zacian"},{"id":"zacian-crowned","name":"Zacian (Crowned)"},{"id":"zamazenta","name":"Zamazenta"},{"id":"zamazenta-crowned","name":"Zamazenta (Crowned)"},{"id":"regidrago","name":"Regidrago"}]}