{"id":"petal-dance","name":"Dança das Pétalas","type":"grass","power":["dex","cha"],"time":"1 ação","pp":5,"duration":"instantâneo","range":"80ft","description":["Você dança ao redor, liberando uma rajada de folhas afiadas contra uma criatura no alcance. Faça uma jogada de ataque à distância, causando 1d10 + MOVE de dano de grama em um acerto. No turno seguinte, você pode escolher usar esta ação novamente para acertar automaticamente, mas se fizer isso, ficará confuso ao final do turno."],"higherLevels":"As rolagens de dano deste movimento mudam para 2d6 no nível 5, 3d6 no nível 10 e 4d6 no nível 17.","damage":{"dice":{"1":"1d10","5":"2d6","10":"3d6","17":"4d6"},"modifier":"MOVE","type":["grass"]},"attack":{"scope":"ranged"},"contest":{"id":"petal-dance","contest":"beauty","appeal":6,"jam":0,"effect":{"id":"2","name":"A very appealing move, but after using this move, the user is more easily startled.","effect":"Pokemon has disadvantage on all CHA Saving Throws for the remainder of the Appeal Rounds."}},"pokemon":[{"id":"bulbasaur","name":"Bulbasaur"},{"id":"venusaur","name":"Venusaur"},{"id":"oddish","name":"Oddish"},{"id":"gloom","name":"Gloom"},{"id":"vileplume","name":"Vileplume"},{"id":"meganium","name":"Meganium"},{"id":"bellossom","name":"Bellossom"},{"id":"sunflora","name":"Sunflora"},{"id":"roselia","name":"Roselia"},{"id":"cherrim","name":"Cherrim"},{"id":"lilligant","name":"Lilligant"},{"id":"maractus","name":"Maractus"},{"id":"flabebe","name":"Flabébé"},{"id":"floette","name":"Floette"},{"id":"florges","name":"Florges"},{"id":"floette-eternal","name":"Floette (Eternal Flower)"},{"id":"comfey","name":"Comfey"},{"id":"lilligant-hisui","name":"Hisuian Lilligant"},{"id":"arboliva","name":"Arboliva"}]}