{"id":"reversal","name":"Reversal","type":"fighting","power":["str","dex"],"time":"1 action","pp":10,"duration":"instantaneous","range":"melee","description":["You unleash an all out attack that is stronger the less HP you have. Make a melee attack roll against a creature, doing 1d6 + MOVE fighting damage on a hit. If you are below 50% of your maximum health, double the damage. If you are at 10% or below of your maximum health, triple the damage. The multiplier for this attack occurs before the multiplier for resistances or vulnerabilities."],"higherLevels":"The damage dice roll for this move changes to 1d12 at level 5, 2d8 at level 10, and 4d6 at level 17.","damage":{"dice":{"1":"1d6","5":"1d12","10":"2d8","17":"4d6"},"modifier":"MOVE","type":["fighting"]},"attack":{"scope":"melee"},"tm":{"id":182,"cost":4900},"contest":{"id":"reversal","contest":"cool","appeal":1,"jam":0,"effect":{"id":"31","name":"Works better the later it is used in a turn.","effect":"1 Appeal point if used first, 2 Appeal points if used second, 3 Appeal points if used third, 4 Appeal points if used last."}},"pokemon":[{"id":"rattata","name":"Rattata"},{"id":"diglett","name":"Diglett"},{"id":"mankey","name":"Mankey"},{"id":"growlithe","name":"Growlithe"},{"id":"hitmonlee","name":"Hitmonlee"},{"id":"rhyhorn","name":"Rhyhorn"},{"id":"kangaskhan","name":"Kangaskhan"},{"id":"scyther","name":"Scyther"},{"id":"cyndaquil","name":"Cyndaquil"},{"id":"sentret","name":"Sentret"},{"id":"pichu","name":"Pichu"},{"id":"yanma","name":"Yanma"},{"id":"heracross","name":"Heracross"},{"id":"houndour","name":"Houndour"},{"id":"miltank","name":"Miltank"},{"id":"torchic","name":"Torchic"},{"id":"taillow","name":"Taillow"},{"id":"swellow","name":"Swellow"},{"id":"vigoroth","name":"Vigoroth"},{"id":"makuhita","name":"Makuhita"},{"id":"hariyama","name":"Hariyama"},{"id":"aron","name":"Aron"},{"id":"meditite","name":"Meditite"},{"id":"medicham","name":"Medicham"},{"id":"riolu","name":"Riolu"},{"id":"victini","name":"Victini"},{"id":"lillipup","name":"Lillipup"},{"id":"herdier","name":"Herdier"},{"id":"stoutland","name":"Stoutland"},{"id":"timburr","name":"Timburr"},{"id":"throh","name":"Throh"},{"id":"sawk","name":"Sawk"},{"id":"escavalier","name":"Escavalier"},{"id":"axew","name":"Axew"},{"id":"mienfoo","name":"Mienfoo"},{"id":"mienshao","name":"Mienshao"},{"id":"bouffalant","name":"Bouffalant"},{"id":"malamar","name":"Malamar"},{"id":"alolan-rattata","name":"Alolan Rattata"},{"id":"alolan-diglett","name":"Alolan Diglett"},{"id":"crabrawler","name":"Crabrawler"},{"id":"crabominable","name":"Crabominable"},{"id":"lycanroc-midnight-form","name":"Lycanroc Midnight Form"},{"id":"passimian","name":"Passimian"},{"id":"togedemaru","name":"Togedemaru"},{"id":"jangmo-o","name":"Jangmo-o"},{"id":"buzzwole","name":"Buzzwole"},{"id":"zapdos-galar","name":"Galarian Zapdos"},{"id":"wooloo","name":"Wooloo"},{"id":"dubwool","name":"Dubwool"},{"id":"clobbopus","name":"Clobbopus"},{"id":"grapploct","name":"Grapploct"},{"id":"falinks","name":"Falinks"},{"id":"growlithe-hisui","name":"Hisuian Growlithe"},{"id":"arcanine-hisui","name":"Hisuian Arcanine"},{"id":"squawkabilly","name":"Squawkabilly"},{"id":"maschiff","name":"Maschiff"},{"id":"mabosstiff","name":"Mabosstiff"}]}