{"id":"shadow-punch","name":"Shadow Punch","type":"ghost","power":["dex","wis"],"time":"1 action","pp":5,"duration":"instantaneous","range":"melee","description":["Você desfere um soco vindo das sombras ao redor, impossível de ser evitado por qualquer criatura. Este movimento tem acerto garantido e causa 1d6 + MOVE de dano fantasma, exceto durante fases de invulnerabilidade de movimentos como Fly, Dig, Bounce, Dive, etc."],"higherLevels":"O dado de dano deste movimento muda para 1d10 no nível 5, 2d8 no nível 10 e 5d4 no nível 17.","damage":{"dice":{"1":"1d6","5":"1d10","10":"2d8","17":"5d4"},"modifier":"MOVE","type":["ghost"]},"contest":{"id":"shadow-punch","contest":"clever","appeal":2,"jam":0,"effect":{"id":"33","name":"Works great if the user goes first this turn.","effect":"4 Appeal points if used first this turn, 2 Appeal points if not used first this turn."}},"pokemon":[{"id":"grimer","name":"Grimer"},{"id":"haunter","name":"Haunter"},{"id":"gengar","name":"Gengar"},{"id":"dusclops","name":"Dusclops"},{"id":"dusknoir","name":"Dusknoir"},{"id":"golett","name":"Golett"},{"id":"golurk","name":"Golurk"},{"id":"marshadow","name":"Marshadow"}]}