{"id":"temper-flare","beta":true,"name":"Temper Flare","type":"fire","power":["str"],"time":"1 ação","pp":5,"duration":"instantâneo","range":"melee","description":["Impulsionado pelo desespero, você ataca o alvo. Faça um ataque corpo a corpo, causando 2d4 + MOVE de dano de fogo em um acerto. Se você errou uma jogada de ataque no turno anterior, adicione um dado de dano adicional à sua rolagem de dano."],"higherLevels":"A rolagem de dados de dano deste movimento muda para 2d6 no nível 5, 2d8 no nível 10 e 3d10 no nível 17.","damage":{"dice":{"1":"2d4","5":"2d6","10":"2d8","17":"3d10"},"modifier":"MOVE","type":["fire"]},"attack":{"scope":"melee"},"tm":{"id":235,"cost":4900},"pokemon":[]}