{"id":"volt-tackle","name":"Volt Tackle","type":"electric","power":["str","dex"],"time":"1 action","pp":10,"duration":"instantaneous","range":"15ft","description":["Você avança em um flash de eletricidade com alcance estendido, atingindo uma criatura. Ao ativar este movimento, você avança 15 pés e faz uma jogada de ataque corpo a corpo contra uma criatura, causando 2d10 + MOVE de dano elétrico em caso de acerto. Em caso de acerto, você também sofre um quarto do dano total (arredondado para baixo) como dano de recuo sem tipo."],"higherLevels":"O dado de dano deste movimento muda para 3d8 no nível 5, 4d10 no nível 10 e 7d8 no nível 17.","damage":{"dice":{"1":"2d10","5":"3d8","10":"4d10","17":"7d8"},"modifier":"MOVE","type":["electric"]},"attack":{"scope":"melee"},"contest":{"id":"volt-tackle","contest":"cool","appeal":6,"jam":0,"effect":{"id":"2","name":"A very appealing move, but after using this move, the user is more easily startled.","effect":"Pokemon has disadvantage on all CHA Saving Throws for the remainder of the Appeal Rounds."}},"pokemon":[{"id":"pichu","name":"Pichu"}]}