{"id":"dragon-energy","name":"Dracoenergía","type":"dragon","power":["str","con"],"time":"1 action","pp":5,"duration":"instantaneous","range":"30ft","description":["Conviertes tu fuerza vital en poder. Realiza un ataque a distancia contra un objetivo a tu alcance, que recibe 1d6 + MOV de daño de tipo Dragón si impactas. Por cada 20 puntos de golpe que tengas actualmente (excluyendo puntos de golpe temporales), infliges 1d6 de daño de tipo Dragón adicional."],"attack":{"scope":"ranged"},"damage":{"dice":{"1":"1d6","5":"1d6","10":"1d6","17":"1d6"},"modifier":"MOVE","type":["dragon"]},"pokemon":[{"id":"regidrago","name":"Regidrago"}]}