{"id":"judgment","name":"Sentencia","type":"varies","power":["str"],"time":"1 action","pp":5,"duration":"instantaneous","range":"100ft","description":["Lanzas poderosos proyectiles de energía pura que caen sobre cualquier criatura en un radio de 80 pies, centrado en un punto dentro del alcance. Cualquier criatura que se encuentre en el área debe realizar una tirada de salvación de Destreza contra tu CD de Movimiento, sufriendo 5d6 + MOV de daño si falla, o la mitad si tiene éxito. El tipo de daño depende de la tabla que lleve el usuario."],"higherLevels":"La tirada de daño de este movimiento pasa a ser 4d10 al nivel 5, 6d10 al nivel 10 y 8d12 al nivel 17.","save":{"attribute":["dex"],"dc":"MOVE"},"damage":{"dice":{"1":"5d6","5":"4d10","10":"6d10","17":"8d12"},"modifier":"MOVE","type":["normal","fighting","flying","poison","ground","rock","bug","ghost","steel","fire","water","grass","electric","psychic","ice","dragon","dark","fairy"]},"contest":{"id":"judgment","contest":"beauty","appeal":3,"jam":0,"effect":{"id":"4","name":"An appealing move that can be used repeatedly without boring the audience.","effect":"No penalty applied for repeating the move."}},"pokemon":[{"id":"arceus","name":"Arceus"}]}