{"id":"mud-bomb","name":"Bomba Fango","type":"ground","power":["str","dex"],"time":"1 action","pp":5,"duration":"instantaneous","range":"40ft","description":["Lanzas una bola de lodo compacta a una criatura. Realiza un ataque a distancia, infligiendo 1d10 + MOV de daño de tipo Tierra si impactas. Al acertar, el objetivo debe realizar una tirada de salvación de Constitución contra tu CD de Movimiento. Si falla, el tiene desventaja en su próxima tirada de ataque. Si el objetivo activa un movimiento que requiere una salvación, el destinatario o destinatarios de dicho movimiento tienen ventaja."],"higherLevels":"La tirada de daño de este movimiento pasa a ser 2d8 al nivel 5, 5d4 al nivel 10 y 4d8 al nivel 17.","damage":{"dice":{"1":"1d10","5":"2d8","10":"5d4","17":"4d8"},"modifier":"MOVE","type":["ground"]},"save":{"attribute":["con"],"dc":"MOVE"},"attack":{"scope":"ranged"},"contest":{"id":"mud-bomb","contest":"cute","appeal":2,"jam":3,"effect":"Startles the last Pokemon to act before the user."},"pokemon":[{"id":"ekans","name":"Ekans"},{"id":"arbok","name":"Arbok"},{"id":"diglett","name":"Diglett"},{"id":"dugtrio","name":"Dugtrio"},{"id":"psyduck","name":"Psyduck"},{"id":"poliwag","name":"Poliwag"},{"id":"poliwhirl","name":"Poliwhirl"},{"id":"grimer","name":"Grimer"},{"id":"muk","name":"Muk"},{"id":"wooper","name":"Wooper"},{"id":"quagsire","name":"Quagsire"},{"id":"swinub","name":"Swinub"},{"id":"piloswine","name":"Piloswine"},{"id":"mudkip","name":"Mudkip"},{"id":"marshtomp","name":"Marshtomp"},{"id":"swampert","name":"Swampert"},{"id":"skitty","name":"Skitty"},{"id":"numel","name":"Numel"},{"id":"barboach","name":"Barboach"},{"id":"whiscash","name":"Whiscash"},{"id":"shellos","name":"Shellos"},{"id":"gastrodon","name":"Gastrodon"},{"id":"happiny","name":"Happiny"},{"id":"croagunk","name":"Croagunk"},{"id":"toxicroak","name":"Toxicroak"},{"id":"mamoswine","name":"Mamoswine"},{"id":"tympole","name":"Tympole"},{"id":"stunfisk","name":"Stunfisk"},{"id":"alolan-diglett","name":"Alolan Diglett"},{"id":"alolan-dugtrio","name":"Alolan Dugtrio"},{"id":"galarian-stunfisk","name":"Galarian Stunfisk"}]}