{"id":"pay-day","name":"Día de Pago","type":"normal","power":["str","dex","cha"],"time":"1 action","pp":10,"duration":"instantaneous","range":"melee","description":["Golpeas a un objetivo, haciendo que se le caiga el monedero. Realiza un ataque cuerpo a cuerpo contra un objetivo, infligiendo 1d6 + MOV de daño de tipo Normal si impactas. Además, una cantidad de dinero equivalente a 10 veces tu nivel queda esparcida por el suelo hasta el final del combate. Esta liberación de fondos solo puede ocurrir una vez por objetivo en cada combate."],"higherLevels":"La tirada de daño de este movimiento pasa a ser 1d12 al nivel 5, 2d8 al nivel 10 y 4d6 al nivel 17.","damage":{"dice":{"1":"1d6","5":"1d12","10":"2d8","17":"4d6"},"modifier":"MOVE","type":["normal"]},"attack":{"scope":"melee"},"contest":{"id":"pay-day","contest":"clever","appeal":2,"jam":0,"effect":{"id":"16","name":"Excites the audience in any kind of contest.","effect":"Raises the crowd meter if successfully performed, regardless of which contest."}},"pokemon":[{"id":"meowth","name":"Meowth"},{"id":"purrloin","name":"Purrloin"},{"id":"alolan-meowth","name":"Alolan Meowth"},{"id":"galarian-meowth","name":"Galarian Meowth"},{"id":"perrserker","name":"Perrserker"}]}