{"id":"frigibax","name":"Frigibax","number":996,"type":["dragon","ice"],"size":"tiny","sr":1,"minLevel":1,"eggGroup":["dragon","mineral"],"gender":"1:1","description":"The Ice Fin Pokémon. Frigibax absorbs heat through its dorsal fin and converts the heat into ice energy. The higher the temperature, the more energy Frigibax stores.","ac":13,"hitDice":"d8","speed":[{"type":"walking","value":25}],"attributes":{"str":14,"dex":11,"con":12,"int":6,"wis":10,"cha":10},"hp":18,"skills":["survival"],"savingThrows":["con"],"senses":[],"abilities":[{"id":"thermal-exchange","name":"Thermal Exchange","description":"This Pokémon cannot be burned. When this Pokémon takes fire-type damage, it makes its next attack with advantage.","hidden":false},{"id":"ice-body","name":"Ice Body","description":"While it is snowing or hailing, this Pokémon heals for an amount of HP equal to its proficiency modifier at the end of each of its turns.","hidden":true}],"moves":{"start":["tackle","leer","dragon-tail"],"level2":["icy-wind"],"level6":["focus-energy","dragon-breath"],"level10":["bite","ice-fang","dragon-claw"],"level14":["take-down","ice-beam"],"level18":["crunch","icicle-crash"],"tm":[14,17,18,42,44,75,88,90],"egg":["icicle-spear","aqua-tail","dragon-rush","freeze-dry"]},"media":{"main":"https://raw.githubusercontent.com/PokeAPI/sprites/master/sprites/pokemon/other/official-artwork/996.png","mainShiny":"https://raw.githubusercontent.com/PokeAPI/sprites/master/sprites/pokemon/other/official-artwork/shiny/996.png","sprite":"https://raw.githubusercontent.com/PokeAPI/sprites/master/sprites/pokemon/996.png","spriteShiny":"https://raw.githubusercontent.com/PokeAPI/sprites/master/sprites/pokemon/shiny/996.png"}}