{"id":"blaze-kick","name":"Blaze Kick","type":"fire","power":["str","dex"],"time":"1 action","pp":5,"duration":"instantaneous","range":"melee","description":["Flames burst from your feet as you deliver a powerful kick. Make a melee attack on a creature, doing 2d6 + MOVE fire damage on a hit. On a natural attack roll of 18 or more, the target is burned. This move scores a critical hit on 19s and 20s."],"higherLevels":"The damage dice roll for this move changes to 2d8 at level 5, 4d6 at level 10, and 6d6 at level 17.","contest":{"id":"blaze-kick","contest":"cool","appeal":3,"jam":0,"effect":"An appealing move that can be used repeatedly without boring the audience."}}