{"id":"captivate","name":"Captivate","type":"normal","power":["wis","cha"],"time":"1 reaction","pp":3,"duration":"instantaneous","range":"40ft","description":["You attempt to charm a creature into pulling its punches. When hit by an attack from a creature of the opposite gender, you may use a reaction to force it to make a CHA save against your Move DC. On a failure, the attack does not hit."],"contest":{"id":"captivate","contest":"cute","appeal":4,"jam":0,"effect":"Makes the audience quickly grow bored when an appeal move has little effect."},"pokemon":[{"id":"butterfree","name":"Butterfree"},{"id":"nidoran-f","name":"Nidoran ♀"},{"id":"nidorina","name":"Nidorina"},{"id":"nidoran-m","name":"Nidoran ♂"},{"id":"nidorino","name":"Nidorino"},{"id":"vulpix","name":"Vulpix"},{"id":"meowth","name":"Meowth"},{"id":"persian","name":"Persian"},{"id":"ponyta","name":"Ponyta"},{"id":"eevee","name":"Eevee"},{"id":"sentret","name":"Sentret"},{"id":"igglybuff","name":"Igglybuff"},{"id":"stantler","name":"Stantler"},{"id":"smoochum","name":"Smoochum"},{"id":"miltank","name":"Miltank"},{"id":"gardevoir","name":"Gardevoir"},{"id":"skitty","name":"Skitty"},{"id":"sableye","name":"Sableye"},{"id":"mawile","name":"Mawile"},{"id":"illumise","name":"Illumise"},{"id":"feebas","name":"Feebas"},{"id":"milotic","name":"Milotic"},{"id":"gorebyss","name":"Gorebyss"},{"id":"luvdisc","name":"Luvdisc"},{"id":"wormadam-plant-cloak","name":"Wormadam Plant Cloak"},{"id":"wormadam-sand-cloak","name":"Wormadam Sand Cloak"},{"id":"wormadam-trash-cloak","name":"Wormadam Trash Cloak"},{"id":"vespiquen","name":"Vespiquen"},{"id":"glameow","name":"Glameow"},{"id":"purugly","name":"Purugly"},{"id":"spiritomb","name":"Spiritomb"},{"id":"finneon","name":"Finneon"},{"id":"lumineon","name":"Lumineon"},{"id":"froslass","name":"Froslass"},{"id":"snivy","name":"Snivy"},{"id":"purrloin","name":"Purrloin"},{"id":"woobat","name":"Woobat"},{"id":"cottonee","name":"Cottonee"},{"id":"zorua","name":"Zorua"},{"id":"minccino","name":"Minccino"},{"id":"gothita","name":"Gothita"},{"id":"litwick","name":"Litwick"},{"id":"flabebe","name":"Flabébé"},{"id":"furfrou","name":"Furfrou"},{"id":"spritzee","name":"Spritzee"},{"id":"alolan-vulpix","name":"Alolan Vulpix"},{"id":"alolan-meowth","name":"Alolan Meowth"},{"id":"alolan-persian","name":"Alolan Persian"},{"id":"popplio","name":"Popplio"},{"id":"brionne","name":"Brionne"},{"id":"primarina","name":"Primarina"},{"id":"oricorio-baile-style","name":"Oricorio Baile Style"},{"id":"oricorio-pom-pom-style","name":"Oricorio Pom-Pom Style"},{"id":"oricorio-pau-style","name":"Oricorio Pa'u Style"},{"id":"oricorio-sensu-style","name":"Oricorio Sensu Style"},{"id":"salazzle","name":"Salazzle"},{"id":"galarian-ponyta","name":"Galarian Ponyta"}]}