{"id":"gastro-acid","name":"Gastro Acid","type":"poison","power":["dex","con"],"time":"1 action","pp":5,"duration":"1 minute","range":"20ft","description":["You hurl stomach acid towards a target. Make a ranged attack. On a hit, the target is covered in the disgusting substance and cannot benefit from the effect of any of its abilities for the duration."],"attack":{"scope":"ranged"},"contest":{"id":"gastro-acid","contest":"tough","appeal":3,"jam":0,"effect":{"id":"10","name":"Brings down the energy of any Pokémon that have already used a move this turn.","effect":"Lowers the crowd meter by the number of Pokemon that raised the crowd meter this turn."}},"pokemon":[{"id":"ekans","name":"Ekans"},{"id":"arbok","name":"Arbok"},{"id":"bellsprout","name":"Bellsprout"},{"id":"weepinbell","name":"Weepinbell"},{"id":"shuckle","name":"Shuckle"},{"id":"gulpin","name":"Gulpin"},{"id":"swalot","name":"Swalot"},{"id":"seviper","name":"Seviper"},{"id":"lileep","name":"Lileep"},{"id":"cradily","name":"Cradily"},{"id":"snivy","name":"Snivy"},{"id":"servine","name":"Servine"},{"id":"serperior","name":"Serperior"},{"id":"joltik","name":"Joltik"},{"id":"galvantula","name":"Galvantula"},{"id":"eelektrik","name":"Eelektrik"},{"id":"eelektross","name":"Eelektross"},{"id":"pyukumuku","name":"Pyukumuku"},{"id":"guzzlord","name":"Guzzlord"},{"id":"chewtle","name":"Chewtle"},{"id":"tarountula","name":"Tarountula"},{"id":"spidops","name":"Spidops"}]}