{"id":"mirror-shot","name":"Mirror Shot","type":"steel","power":["str","dex"],"time":"1 action","pp":5,"duration":"instantaneous","range":"40ft","description":["You loose a damaging flash of light from your polished body. Make a ranged attack on a creature, dealing 1d10 + MOVE steel damage on a hit. On a hit, the target must make a CON save against your Move DC. On a failure, the target has disadvantage on its next attack roll."],"higherLevels":"The damage dice roll for this move changes to 2d8 at level 5, 5d4 at level 10, and 4d8 at level 17.","damage":{"dice":{"1":"1d10","5":"2d8","10":"5d4","17":"4d8"},"modifier":"MOVE","type":["steel"]},"save":{"attribute":["con"],"dc":"MOVE"},"attack":{"scope":"ranged"},"contest":{"id":"mirror-shot","contest":"beauty","appeal":2,"jam":3,"effect":"Startles the last Pokemon to act before the user."},"pokemon":[{"id":"magnemite","name":"Magnemite"},{"id":"magneton","name":"Magneton"},{"id":"forretress","name":"Forretress"},{"id":"wormadam-trash-cloak","name":"Wormadam Trash Cloak"},{"id":"magnezone","name":"Magnezone"},{"id":"vanillite","name":"Vanillite"},{"id":"vanillish","name":"Vanillish"},{"id":"vanilluxe","name":"Vanilluxe"},{"id":"ferroseed","name":"Ferroseed"},{"id":"ferrothorn","name":"Ferrothorn"},{"id":"klink","name":"Klink"},{"id":"klang","name":"Klang"},{"id":"klinklang","name":"Klinklang"},{"id":"klefki","name":"Klefki"},{"id":"necrozma","name":"Necrozma"},{"id":"dusk-mane-necrozma","name":"Dusk Mane Necrozma"},{"id":"dawn-wings-necrozma","name":"Dawn Wings Necrozma"},{"id":"ultra-necrozma","name":"Ultra Necrozma"},{"id":"magearna","name":"Magearna"}]}