{"id":"moongeist-beam","name":"Moongeist Beam","type":"ghost","power":["dex","wis"],"time":"1 action","pp":5,"duration":"instantaneous","range":"self (100ft line)","description":["You emit a sinister ray that explodes out from you in a 100 foot line, 5 feet wide. All creatures caught in the blast must make a DEX save against your Move DC, taking 5d6 + MOVE ghost damage on a failure or half as much on a success. This attack ignores any of the creatures abilities that would affect the user's ability to hit or deal full damage."],"higherLevels":"The damage dice roll for this move changes to 4d10 at level 5, 6d10 at level 10, and 8d12 at level 17."}