{"id":"pin-missile","name":"Pin Missile","type":"bug","power":["dex"],"time":"1 action","pp":10,"duration":"instantaneous","range":"60ft","description":["You strike a creature with sharp projectiles in quick succession. Make a ranged attack roll, doing 1d4 + MOVE bug damage on a hit. After successfully hitting a target, roll a d4. On a result of 3 or 4, another projectile hits again for an additional 1d4 bug damage. Continue this process until you fail to roll a 3 or 4 on the d4 roll, up to a maximum of four additional hits."],"higherLevels":"The damage dice rolls for this move change to 2d4 at level 5, 1d12 at level 10, and 4d4 at level 17.","contest":{"id":"pin-missile","contest":"cool","appeal":1,"jam":0,"effect":"Effectiveness varies depending on when it is used."},"pokemon":[{"id":"beedrill","name":"Beedrill"},{"id":"jolteon","name":"Jolteon"},{"id":"spinarak","name":"Spinarak"},{"id":"ariados","name":"Ariados"},{"id":"pineco","name":"Pineco"},{"id":"qwilfish","name":"Qwilfish"},{"id":"heracross","name":"Heracross"},{"id":"zigzagoon","name":"Zigzagoon"},{"id":"cacnea","name":"Cacnea"},{"id":"cacturne","name":"Cacturne"},{"id":"budew","name":"Budew"},{"id":"skorupi","name":"Skorupi"},{"id":"drapion","name":"Drapion"},{"id":"venipede","name":"Venipede"},{"id":"maractus","name":"Maractus"},{"id":"joltik","name":"Joltik"},{"id":"ferroseed","name":"Ferroseed"},{"id":"ferrothorn","name":"Ferrothorn"},{"id":"chespin","name":"Chespin"},{"id":"quilladin","name":"Quilladin"},{"id":"chesnaught","name":"Chesnaught"},{"id":"mareanie","name":"Mareanie"},{"id":"toxapex","name":"Toxapex"},{"id":"golisopod","name":"Golisopod"},{"id":"togedemaru","name":"Togedemaru"},{"id":"galarian-zigzagoon","name":"Galarian Zigzagoon"},{"id":"galarian-linoone","name":"Galarian Linoone"},{"id":"obstagoon","name":"Obstagoon"},{"id":"qwilfish-hisui","name":"Hisuian Qwilfish"},{"id":"overqwil","name":"Overqwil"},{"id":"iron-thorns","name":"Iron Thorns"}]}