{"id":"poison-fang","name":"Poison Fang","type":"poison","power":["str","dex"],"time":"1 action","pp":10,"duration":"instantaneous","range":"melee","description":["You lash forward with poisonous venom. Make a melee attack roll against a creature, dealing 1d8 + MOVE poison damage on a hit, forcing the target to make a CON save against your Move DC. On a failure, the creature is poisoned. A creature poisoned by this move takes double the normal poison damage at the end of each of its turns."],"higherLevels":"The damage dice roll for this move changes to 2d6 at level 5, 4d4 at level 10, and 3d10 at level 17.","contest":{"id":"poison-fang","contest":"clever","appeal":4,"jam":0,"effect":"Quite an appealing move."}}