{"id":"quash","name":"Quash","type":"dark","power":["str","wis"],"time":"1 action","pp":10,"duration":"instantaneous","range":"30ft","description":["You send dark energy at a creature in range, reducing their will to fight. The target must make a WIS save against your Move DC. On a failure, it must move to the bottom of the initiative order for this round only. Targets that have already taken their turn in this round are unaffected."],"contest":{"id":"quash","contest":"clever","appeal":3,"jam":0,"effect":"Causes the user to move earlier on the next turn."}}