{"id":"smart-strike","name":"Smart Strike","type":"steel","power":["str","int"],"time":"1 action","pp":5,"duration":"instantaneous","range":"melee","description":["You pinpoint the perfect place to strike a creature with a horn as strong as steel. This move is guaranteed to hit for 1d6 + MOVE steel damage, unless during the invulnerable stage of Fly, Dig, Bounce, Dive, etc. moves."],"higherLevels":"The damage dice roll for this move changes to 1d10 at level 5, 2d8 at level 10, and 5d4 at level 17."}