{"id":"soak","name":"Soak","type":"water","power":["str","con"],"time":"1 action","pp":10,"duration":"3 rounds","range":"50ft","description":["You fire a torrent of water at a creature that leaves lasting effects. Force a target in range to make a CON save against your Move DC. On a failure, its type changes to water through its next three full turns in battle."],"save":{"attribute":["con"],"dc":"MOVE"},"contest":{"id":"soak","contest":"cute","appeal":2,"jam":1,"effect":"Badly startles Pokemon that the audience has high expectations of."},"pokemon":[{"id":"psyduck","name":"Psyduck"},{"id":"golduck","name":"Golduck"},{"id":"goldeen","name":"Goldeen"},{"id":"seaking","name":"Seaking"},{"id":"chinchou","name":"Chinchou"},{"id":"remoraid","name":"Remoraid"},{"id":"octillery","name":"Octillery"},{"id":"wingull","name":"Wingull"},{"id":"pelipper","name":"Pelipper"},{"id":"azurill","name":"Azurill"},{"id":"wailmer","name":"Wailmer"},{"id":"wailord","name":"Wailord"},{"id":"luvdisc","name":"Luvdisc"},{"id":"buizel","name":"Buizel"},{"id":"finneon","name":"Finneon"},{"id":"lumineon","name":"Lumineon"},{"id":"basculin","name":"Basculin"},{"id":"alomomola","name":"Alomomola"},{"id":"wishiwashi-solo-form","name":"Wishiwashi Solo Form"},{"id":"wishiwashi-school-form","name":"Wishiwashi School Form"},{"id":"araquanid","name":"Araquanid"},{"id":"pyukumuku","name":"Pyukumuku"},{"id":"tapu-fini","name":"Tapu Fini"},{"id":"sobble","name":"Sobble"},{"id":"drizzile","name":"Drizzile"},{"id":"inteleon","name":"Inteleon"},{"id":"clobbopus","name":"Clobbopus"},{"id":"basculegion-m","name":"Basculegion ♂"},{"id":"basculegion-f","name":"Basculegion ♀"},{"id":"tadbulb","name":"Tadbulb"},{"id":"dondozo","name":"Dondozo"},{"id":"tatsugiri","name":"Tatsugiri"}]}