{"id":"whirlpool","name":"Whirlpool","type":"water","power":["str"],"time":"1 action","pp":10,"duration":"instantaneous","range":"60ft","description":["You create a wave of water that swirls around a creature in range. Make a ranged attack roll. On a hit, the target takes 1d6 + MOVE water damage and is restrained. At the beginning of each of its turns, it may attempt to escape with a STR save against your Move DC. On each successive turn, if the creature is still restrained, you may use this move again (as an action) and automatically hit."],"higherLevels":"The damage dice roll for this move changes to 1d10 at level 5, 2d8 at level 10, and 5d4 at level 17."}