{"id":"bulbasaur","name":"Bulbasaur","number":1,"type":["grass","poison"],"size":"tiny","sr":0.5,"minLevel":1,"eggGroup":["monster","grass"],"gender":"1:7","evolution":{"stage":"1","maxStage":"3","to":[{"id":"ivysaur","conditions":[{"type":"level","value":6}],"effects":[{"type":"asi","value":6}]}]},"description":"The Seed Pokémon. It can go for days without eating a single morsel. In the bulb on its back, it stores energy.","ac":13,"hp":17,"hitDice":"d6","speed":[{"type":"walking","value":30}],"attributes":{"str":13,"dex":12,"con":12,"int":6,"wis":10,"cha":10},"skills":["athletics","nature"],"savingThrows":["str"],"senses":[],"abilities":[{"id":"overgrow","name":"Overgrow","description":"This Pokémon doubles its STAB bonus when it has 25% or less of its maximum health.","hidden":false},{"id":"chlorophyll","name":"Chlorophyll","description":"This Pokémon’s speed is doubled in harsh sunlight.","hidden":true}],"moves":{"start":["tackle","growl"],"level2":["vine-whip","leech-seed"],"level6":["poison-powder","sleep-powder","take-down","razor-leaf"],"level10":["sweet-scent","growth","double-edge"],"level14":["worry-seed","synthesis"],"level18":["seed-bomb"],"tm":[1,6,9,10,11,16,17,20,21,22,27,32,36,42,44,45,48,49,53,75,86,87,88,90,96,100],"egg":["amnesia","charm","curse","endure","giga-drain","grass-whistle","grassy-terrain","ingrain","leaf-storm","light-screen","magical-leaf","nature-power","petal-dance","power-whip","safeguard","skull-bash","sludge"]},"media":{"main":"https://raw.githubusercontent.com/PokeAPI/sprites/master/sprites/pokemon/other/official-artwork/1.png","sprite":"https://raw.githubusercontent.com/PokeAPI/sprites/master/sprites/pokemon/1.png","mainShiny":"https://raw.githubusercontent.com/PokeAPI/sprites/master/sprites/pokemon/other/official-artwork/shiny/1.png","spriteShiny":"https://raw.githubusercontent.com/PokeAPI/sprites/master/sprites/pokemon/shiny/1.png"}}