{"id":"eiscue","name":"Eiscue","number":875,"type":["ice"],"size":"medium","sr":6,"minLevel":5,"eggGroup":["water-1","field"],"gender":"1:1","description":"The Penguin Pokémon. It drifted in on the flow of ocean waters from a frigid place. It keeps its head iced constantly to make sure it stays nice and cold.","ac":18,"hitDice":"d8","speed":[{"type":"walking","value":20},{"type":"swimming","value":30}],"attributes":{"str":13,"dex":13,"con":15,"int":6,"wis":12,"cha":10},"hp":56,"skills":["nature","survival"],"savingThrows":["con"],"senses":[],"abilities":[{"id":"ice-face","name":"Ice Face","description":"This Pokémon has two forms: Ice Form and No-Ice Form. When in Ice Form, the first time this pokémon takes damage, it takes half that damage but transforms into No-Ice Form. When in No-Ice Form, this pokemon's AC is decreased by 3 and each of its movement speeds are increased by 5 ft. This Pokémon reverts back to Ice Form after a short rest, or on the start of its turn when in the hail.","hidden":false}],"moves":{"start":["tackle","powder-snow","mist","weather-ball"],"level6":["icy-wind"],"level10":["headbutt","amnesia"],"level14":["freeze-dry","snowscape","aurora-veil"],"level18":["surf","blizzard","hail"],"tm":[13,15,17,18,33,42,44,45,48,68,88,90,98]},"media":{"main":"https://raw.githubusercontent.com/PokeAPI/sprites/master/sprites/pokemon/other/official-artwork/875.png","sprite":"https://raw.githubusercontent.com/PokeAPI/sprites/master/sprites/pokemon/875.png"}}