{"id":"gyarados","name":"Gyarados","number":130,"type":["water","flying"],"size":"huge","sr":10,"minLevel":8,"eggGroup":["water 2","dragon"],"gender":"1:1","evolution":{"stage":"2","maxStage":"2"},"description":"The Atrocious Pokémon. Brutally vicious and enormously destructive. Known for totally destroying cities in ancient times.","ac":16,"hp":80,"hitDice":"d12","speed":[{"type":"walking","value":30},{"type":"swimming","value":40},{"type":"flying","value":30}],"attributes":{"str":"18","dex":"16","con":"16","int":"6","wis":"12","cha":"10"},"skills":["athletics","intimidation"],"savingThrows":["str","con"],"senses":[],"abilities":[{"id":"intimidate","name":"Intimidate","description":"Once per short rest, you can impose disadvantage on an enemy attack roll of your choice.","hidden":false},{"id":"moxie","name":"Moxie","description":"Upon causing an opponent to faint, this Pokémon may immediately take another action.","hidden":true}],"moves":{"start":["bite","thrash"],"level10":["leer","twister","ice-fang"],"level14":["aqua-tail","scary-face","dragon-rage","crunch"],"level18":["hydro-pump","dragon-dance","hurricane","rain-dance","hyper-beam"],"tm":[5,6,7,10,12,13,14,15,17,18,21,24,25,26,27,32,35,37,38,41,42,44,45,48,55,59,66,68,71,73,78,82,87,88,90,94,97,98,100]}}