{"id":"palpitoad","name":"Palpitoad","number":536,"type":["water","ground"],"size":"small","sr":5,"minLevel":5,"eggGroup":["water 1"],"gender":"1:1","description":"The Vibration Pokémon. It lives in the water and on land. It uses its long, sticky tongue to capture prey.","ac":14,"hp":50,"hitDice":"d8","speed":[{"type":"walking","value":15},{"type":"swimming","value":25}],"attributes":{"str":13,"dex":14,"con":15,"int":6,"wis":12,"cha":10},"skills":["survival"],"savingThrows":["dex"],"senses":[],"abilities":[{"id":"swift-swim","name":"Swift Swim","description":"This Pokémon's speed is doubled in rainy conditions.","hidden":false},{"id":"hydration","name":"Hydration","description":"This Pokémon is unaffected by negative status ailments in water or during rainy conditions.","hidden":false},{"id":"water-absorb","name":"Water Absorb","description":"This Pokémon takes no damage from water or water-type attacks. Instead, half of any water damage done is absorbed, restoring the Pokémon's HP.","hidden":true}],"moves":{"start":["bubble","growl","round","supersonic","bubble-beam"],"level6":["mud-shot","aqua-ring"],"level10":["uproar","muddy-water"],"level14":["rain-dance","flail"],"level18":["echoed-voice","hydro-pump","hyper-voice"],"tm":[6,7,10,17,18,21,27,32,34,36,42,44,45,48,49,55,78,83,87,88,90,94,100]},"media":{"main":"https://raw.githubusercontent.com/PokeAPI/sprites/master/sprites/pokemon/other/official-artwork/536.png","sprite":"https://raw.githubusercontent.com/PokeAPI/sprites/master/sprites/pokemon/536.png","mainShiny":"https://raw.githubusercontent.com/PokeAPI/sprites/master/sprites/pokemon/other/official-artwork/shiny/536.png","spriteShiny":"https://raw.githubusercontent.com/PokeAPI/sprites/master/sprites/pokemon/shiny/536.png"},"habitat":{"biomes":["pond","riverside","swamp"]},"evolution":{"stage":2,"maxStage":3,"to":[{"id":"seismitoad","conditions":[{"type":"level","value":14}],"effects":[{"type":"asi","value":10}]}],"from":["tympole"]}}