{"id":"jaw-lock","name":"Jaw Lock","type":"dark","power":["str"],"time":"1 action","pp":5,"duration":"instantaneous","range":"melee","description":["You latch onto a foe, never to let go. Make a melee attack against a target, doing 2d6 + MOVE dark damage on a hit.","On a hit, you grapple the target. On your turn, you may activate this move against a target grappled this way to deal 2d6 + MOVE dark damage. This move can grapple targets up to two sizes larger than you."],"higherLevels":"The damage dice roll for this move changes to 2d8 at level 5, 4d6 at level 10, and 6d6 at level 17.","damage":{"dice":{"1":"2d6","5":"2d8","10":"4d6","17":"6d6"},"modifier":"MOVE","type":["dark"]},"attack":{"scope":"melee"},"pokemon":[{"id":"chewtle","name":"Chewtle"},{"id":"drednaw","name":"Drednaw"},{"id":"maschiff","name":"Maschiff"},{"id":"mabosstiff","name":"Mabosstiff"}]}